setup.py
easypython/__init__.py
easypython/__main__.py
easypython/core.py
easypython.egg-info/PKG-INFO
easypython.egg-info/SOURCES.txt
easypython.egg-info/dependency_links.txt
easypython.egg-info/entry_points.txt
easypython.egg-info/not-zip-safe
easypython.egg-info/requires.txt
easypython.egg-info/top_level.txt
easypython/modules/__init__.py
easypython/modules/run_module.py
easypython/utils/__init__.py
easypython/utils/args_parser.py
easypython/utils/config_parser.py
easypython/utils/functions.py
easypython/utils/logger.py